txtcli/__init__.py
txtcli/gui.py
txtcli/main.py
txtcli/model.py
txtcli/util.py
txtcli-0.1.3.dist-info/entry_points.txt
txtcli-0.1.3.dist-info/LICENSE
txtcli-0.1.3.dist-info/WHEEL
txtcli-0.1.3.dist-info/METADATA
txtcli-0.1.3.dist-info/RECORD
