Metadata-Version: 2.1
Name: txtcli
Version: 0.1.3
Summary: txt-cli: The CLI tool for ahui2016/txt
Author-email: ahui <102419@gmail.com>
Requires-Python: >=3.10
Classifier: License :: OSI Approved :: MIT License
Requires-Dist: arrow
Requires-Dist: click
Requires-Dist: appdirs
Requires-Dist: pyperclip
Requires-Dist: requests
Project-URL: Home, https://github.com/ahui2016/txt-cli
